Compiled from "StringOperation.java"
public class StringOperation {
  public StringOperation();
    descriptor: ()V
    Code:
       0: aload_0
       1: invokespecial #1                  // Method java/lang/Object."<init>":()V
       4: return

  private java.lang.String newString();
    descriptor: ()Ljava/lang/String;
    Code:
       0: ldc           #2                  // String string
       2: areturn

  private java.lang.String newString1();
    descriptor: ()Ljava/lang/String;
    Code:
       0: new           #3                  // class java/lang/String
       3: dup
       4: ldc           #2                  // String string
       6: invokespecial #4                  // Method java/lang/String."<init>":(Ljava/lang/String;)V
       9: areturn

  private java.lang.String newString2(java.lang.String);
    descriptor: (Ljava/lang/String;)Ljava/lang/String;
    Code:
       0: aload_1
       1: areturn

  private java.lang.String newString3(java.lang.String);
    descriptor: (Ljava/lang/String;)Ljava/lang/String;
    Code:
       0: new           #3                  // class java/lang/String
       3: dup
       4: aload_1
       5: invokespecial #4                  // Method java/lang/String."<init>":(Ljava/lang/String;)V
       8: areturn

  private java.lang.String string();
    descriptor: ()Ljava/lang/String;
    Code:
       0: ldc           #5                  // String iamString
       2: areturn

  private java.lang.String string1();
    descriptor: ()Ljava/lang/String;
    Code:
       0: ldc           #6                  // String i
       2: astore_1
       3: new           #7                  // class java/lang/StringBuilder
       6: dup
       7: invokespecial #8                  // Method java/lang/StringBuilder."<init>":()V
      10: aload_1
      11: invokevirtual #9                  // Method java/lang/StringBuilder.append:(Ljava/lang/String;)Ljava/lang/StringBuilder;
      14: ldc           #10                 // String am
      16: invokevirtual #9                  // Method java/lang/StringBuilder.append:(Ljava/lang/String;)Ljava/lang/StringBuilder;
      19: invokevirtual #11                 // Method java/lang/StringBuilder.toString:()Ljava/lang/String;
      22: astore_1
      23: new           #7                  // class java/lang/StringBuilder
      26: dup
      27: invokespecial #8                  // Method java/lang/StringBuilder."<init>":()V
      30: aload_1
      31: invokevirtual #9                  // Method java/lang/StringBuilder.append:(Ljava/lang/String;)Ljava/lang/StringBuilder;
      34: ldc           #12                 // String String
      36: invokevirtual #9                  // Method java/lang/StringBuilder.append:(Ljava/lang/String;)Ljava/lang/StringBuilder;
      39: invokevirtual #11                 // Method java/lang/StringBuilder.toString:()Ljava/lang/String;
      42: astore_1
      43: aload_1
      44: areturn

  private java.lang.String stringWithParam(java.lang.String);
    descriptor: (Ljava/lang/String;)Ljava/lang/String;
    Code:
       0: new           #7                  // class java/lang/StringBuilder
       3: dup
       4: invokespecial #8                  // Method java/lang/StringBuilder."<init>":()V
       7: ldc           #6                  // String i
       9: invokevirtual #9                  // Method java/lang/StringBuilder.append:(Ljava/lang/String;)Ljava/lang/StringBuilder;
      12: aload_1
      13: invokevirtual #9                  // Method java/lang/StringBuilder.append:(Ljava/lang/String;)Ljava/lang/StringBuilder;
      16: ldc           #12                 // String String
      18: invokevirtual #9                  // Method java/lang/StringBuilder.append:(Ljava/lang/String;)Ljava/lang/StringBuilder;
      21: invokevirtual #11                 // Method java/lang/StringBuilder.toString:()Ljava/lang/String;
      24: areturn

  private java.lang.String stringWithParam1(java.lang.String);
    descriptor: (Ljava/lang/String;)Ljava/lang/String;
    Code:
       0: ldc           #6                  // String i
       2: astore_2
       3: new           #7                  // class java/lang/StringBuilder
       6: dup
       7: invokespecial #8                  // Method java/lang/StringBuilder."<init>":()V
      10: aload_2
      11: invokevirtual #9                  // Method java/lang/StringBuilder.append:(Ljava/lang/String;)Ljava/lang/StringBuilder;
      14: aload_1
      15: invokevirtual #9                  // Method java/lang/StringBuilder.append:(Ljava/lang/String;)Ljava/lang/StringBuilder;
      18: invokevirtual #11                 // Method java/lang/StringBuilder.toString:()Ljava/lang/String;
      21: astore_2
      22: new           #7                  // class java/lang/StringBuilder
      25: dup
      26: invokespecial #8                  // Method java/lang/StringBuilder."<init>":()V
      29: aload_2
      30: invokevirtual #9                  // Method java/lang/StringBuilder.append:(Ljava/lang/String;)Ljava/lang/StringBuilder;
      33: ldc           #12                 // String String
      35: invokevirtual #9                  // Method java/lang/StringBuilder.append:(Ljava/lang/String;)Ljava/lang/StringBuilder;
      38: invokevirtual #11                 // Method java/lang/StringBuilder.toString:()Ljava/lang/String;
      41: astore_2
      42: aload_2
      43: areturn

  private java.lang.String stringBuilder();
    descriptor: ()Ljava/lang/String;
    Code:
       0: new           #7                  // class java/lang/StringBuilder
       3: dup
       4: invokespecial #8                  // Method java/lang/StringBuilder."<init>":()V
       7: ldc           #6                  // String i
       9: invokevirtual #9                  // Method java/lang/StringBuilder.append:(Ljava/lang/String;)Ljava/lang/StringBuilder;
      12: ldc           #10                 // String am
      14: invokevirtual #9                  // Method java/lang/StringBuilder.append:(Ljava/lang/String;)Ljava/lang/StringBuilder;
      17: ldc           #12                 // String String
      19: invokevirtual #9                  // Method java/lang/StringBuilder.append:(Ljava/lang/String;)Ljava/lang/StringBuilder;
      22: invokevirtual #11                 // Method java/lang/StringBuilder.toString:()Ljava/lang/String;
      25: areturn
}
